{
    "description": "TYPE: CUSTOM\nMaterial Theme Builder export 2025-06-17 05:28:01",
    "seed": "#FF5722",
    "coreColors": {
        "primary": "#FF5722",
        "secondary": "#795548",
        "tertiary": "#FF9800",
        "error": "#D32F2F",
        "neutral": "#FFF3E0",
        "neutralVariant": "#9E9E9E"
    },
    "extendedColors": [],
    "schemes": {
        "light": {
            "primary": "#B02F00",
            "surfaceTint": "#B02F00",
            "onPrimary": "#FFFFFF",
            "primaryContainer": "#FF5722",
            "onPrimaryContainer": "#541200",
            "secondary": "#5F3E32",
            "onSecondary": "#FFFFFF",
            "secondaryContainer": "#795548",
            "onSecondaryContainer": "#FDCDBC",
            "tertiary": "#8B5000",
            "onTertiary": "#FFFFFF",
            "tertiaryContainer": "#FF9800",
            "onTertiaryContainer": "#653900",
            "error": "#AF101A",
            "onError": "#FFFFFF",
            "errorContainer": "#D32F2F",
            "onErrorContainer": "#FFF2F0",
            "background": "#FFF8F6",
            "onBackground": "#271813",
            "surface": "#FDF8F6",
            "onSurface": "#1C1B1A",
            "surfaceVariant": "#E0E3E3",
            "onSurfaceVariant": "#444748",
            "outline": "#747878",
            "outlineVariant": "#C4C7C7",
            "shadow": "#000000",
            "scrim": "#000000",
            "inverseSurface": "#32302F",
            "inverseOnSurface": "#F5F0ED",
            "inversePrimary": "#FFB5A0",
            "primaryFixed": "#FFDBD1",
            "onPrimaryFixed": "#3B0900",
            "primaryFixedDim": "#FFB5A0",
            "onPrimaryFixedVariant": "#862200",
            "secondaryFixed": "#FFDBCF",
            "onSecondaryFixed": "#2E150B",
            "secondaryFixedDim": "#EBBCAC",
            "onSecondaryFixedVariant": "#603F33",
            "tertiaryFixed": "#FFDCBE",
            "onTertiaryFixed": "#2C1600",
            "tertiaryFixedDim": "#FFB870",
            "onTertiaryFixedVariant": "#693C00",
            "surfaceDim": "#DED9D7",
            "surfaceBright": "#FDF8F6",
            "surfaceContainerLowest": "#FFFFFF",
            "surfaceContainerLow": "#F8F3F0",
            "surfaceContainer": "#F2EDEA",
            "surfaceContainerHigh": "#ECE7E5",
            "surfaceContainerHighest": "#E6E2DF"
        },
        "light-medium-contrast": {
            "primary": "#691800",
            "surfaceTint": "#B02F00",
            "onPrimary": "#FFFFFF",
            "primaryContainer": "#CA3700",
            "onPrimaryContainer": "#FFFFFF",
            "secondary": "#4D2F23",
            "onSecondary": "#FFFFFF",
            "secondaryContainer": "#795548",
            "onSecondaryContainer": "#FFFFFF",
            "tertiary": "#522D00",
            "onTertiary": "#FFFFFF",
            "tertiaryContainer": "#9F5D00",
            "onTertiaryContainer": "#FFFFFF",
            "error": "#73000A",
            "onError": "#FFFFFF",
            "errorContainer": "#CF2C2D",
            "onErrorContainer": "#FFFFFF",
            "background": "#FFF8F6",
            "onBackground": "#271813",
            "surface": "#FDF8F6",
            "onSurface": "#121110",
            "surfaceVariant": "#E0E3E3",
            "onSurfaceVariant": "#333737",
            "outline": "#4F5354",
            "outlineVariant": "#6A6E6E",
            "shadow": "#000000",
            "scrim": "#000000",
            "inverseSurface": "#32302F",
            "inverseOnSurface": "#F5F0ED",
            "inversePrimary": "#FFB5A0",
            "primaryFixed": "#CA3700",
            "onPrimaryFixed": "#FFFFFF",
            "primaryFixedDim": "#9F2A00",
            "onPrimaryFixedVariant": "#FFFFFF",
            "secondaryFixed": "#8A6457",
            "onSecondaryFixed": "#FFFFFF",
            "secondaryFixedDim": "#6F4C40",
            "onSecondaryFixedVariant": "#FFFFFF",
            "tertiaryFixed": "#9F5D00",
            "onTertiaryFixed": "#FFFFFF",
            "tertiaryFixedDim": "#7D4800",
            "onTertiaryFixedVariant": "#FFFFFF",
            "surfaceDim": "#CAC6C3",
            "surfaceBright": "#FDF8F6",
            "surfaceContainerLowest": "#FFFFFF",
            "surfaceContainerLow": "#F8F3F0",
            "surfaceContainer": "#ECE7E5",
            "surfaceContainerHigh": "#E0DCD9",
            "surfaceContainerHighest": "#D5D1CE"
        },
        "light-high-contrast": {
            "primary": "#581300",
            "surfaceTint": "#B02F00",
            "onPrimary": "#FFFFFF",
            "primaryContainer": "#8B2300",
            "onPrimaryContainer": "#FFFFFF",
            "secondary": "#41251A",
            "onSecondary": "#FFFFFF",
            "secondaryContainer": "#624135",
            "onSecondaryContainer": "#FFFFFF",
            "tertiary": "#442500",
            "onTertiary": "#FFFFFF",
            "tertiaryContainer": "#6D3E00",
            "onTertiaryContainer": "#FFFFFF",
            "error": "#600007",
            "onError": "#FFFFFF",
            "errorContainer": "#980010",
            "onErrorContainer": "#FFFFFF",
            "background": "#FFF8F6",
            "onBackground": "#271813",
            "surface": "#FDF8F6",
            "onSurface": "#000000",
            "surfaceVariant": "#E0E3E3",
            "onSurfaceVariant": "#000000",
            "outline": "#292D2D",
            "outlineVariant": "#464A4A",
            "shadow": "#000000",
            "scrim": "#000000",
            "inverseSurface": "#32302F",
            "inverseOnSurface": "#FFFFFF",
            "inversePrimary": "#FFB5A0",
            "primaryFixed": "#8B2300",
            "onPrimaryFixed": "#FFFFFF",
            "primaryFixedDim": "#631600",
            "onPrimaryFixedVariant": "#FFFFFF",
            "secondaryFixed": "#624135",
            "onSecondaryFixed": "#FFFFFF",
            "secondaryFixedDim": "#492B20",
            "onSecondaryFixedVariant": "#FFFFFF",
            "tertiaryFixed": "#6D3E00",
            "onTertiaryFixed": "#FFFFFF",
            "tertiaryFixedDim": "#4D2A00",
            "onTertiaryFixedVariant": "#FFFFFF",
            "surfaceDim": "#BCB8B6",
            "surfaceBright": "#FDF8F6",
            "surfaceContainerLowest": "#FFFFFF",
            "surfaceContainerLow": "#F5F0ED",
            "surfaceContainer": "#E6E2DF",
            "surfaceContainerHigh": "#D8D3D1",
            "surfaceContainerHighest": "#CAC6C3"
        },
        "dark": {
            "primary": "#FFB5A0",
            "surfaceTint": "#FFB5A0",
            "onPrimary": "#5F1500",
            "primaryContainer": "#FF5722",
            "onPrimaryContainer": "#541200",
            "secondary": "#EBBCAC",
            "onSecondary": "#46291E",
            "secondaryContainer": "#795548",
            "onSecondaryContainer": "#FDCDBC",
            "tertiary": "#FFC081",
            "onTertiary": "#4A2800",
            "tertiaryContainer": "#FF9800",
            "onTertiaryContainer": "#653900",
            "error": "#FFB3AC",
            "onError": "#680008",
            "errorContainer": "#D32F2F",
            "onErrorContainer": "#FFF2F0",
            "background": "#1E100C",
            "onBackground": "#FADCD4",
            "surface": "#141312",
            "onSurface": "#E6E2DF",
            "surfaceVariant": "#444748",
            "onSurfaceVariant": "#C4C7C7",
            "outline": "#8E9192",
            "outlineVariant": "#444748",
            "shadow": "#000000",
            "scrim": "#000000",
            "inverseSurface": "#E6E2DF",
            "inverseOnSurface": "#32302F",
            "inversePrimary": "#B02F00",
            "primaryFixed": "#FFDBD1",
            "onPrimaryFixed": "#3B0900",
            "primaryFixedDim": "#FFB5A0",
            "onPrimaryFixedVariant": "#862200",
            "secondaryFixed": "#FFDBCF",
            "onSecondaryFixed": "#2E150B",
            "secondaryFixedDim": "#EBBCAC",
            "onSecondaryFixedVariant": "#603F33",
            "tertiaryFixed": "#FFDCBE",
            "onTertiaryFixed": "#2C1600",
            "tertiaryFixedDim": "#FFB870",
            "onTertiaryFixedVariant": "#693C00",
            "surfaceDim": "#141312",
            "surfaceBright": "#3B3937",
            "surfaceContainerLowest": "#0F0E0D",
            "surfaceContainerLow": "#1C1B1A",
            "surfaceContainer": "#211F1E",
            "surfaceContainerHigh": "#2B2A28",
            "surfaceContainerHighest": "#363433"
        },
        "dark-medium-contrast": {
            "primary": "#FFD2C6",
            "surfaceTint": "#FFB5A0",
            "onPrimary": "#4C0F00",
            "primaryContainer": "#FF5722",
            "onPrimaryContainer": "#000000",
            "secondary": "#FFD3C4",
            "onSecondary": "#3A1E14",
            "secondaryContainer": "#B18778",
            "onSecondaryContainer": "#000000",
            "tertiary": "#FFD5AE",
            "onTertiary": "#3B1F00",
            "tertiaryContainer": "#FF9800",
            "onTertiaryContainer": "#3A1F00",
            "error": "#FFD2CD",
            "onError": "#540005",
            "errorContainer": "#FF544E",
            "onErrorContainer": "#000000",
            "background": "#1E100C",
            "onBackground": "#FADCD4",
            "surface": "#141312",
            "onSurface": "#FFFFFF",
            "surfaceVariant": "#444748",
            "onSurfaceVariant": "#DADDDD",
            "outline": "#AFB2B3",
            "outlineVariant": "#8D9191",
            "shadow": "#000000",
            "scrim": "#000000",
            "inverseSurface": "#E6E2DF",
            "inverseOnSurface": "#2B2A28",
            "inversePrimary": "#892200",
            "primaryFixed": "#FFDBD1",
            "onPrimaryFixed": "#280500",
            "primaryFixedDim": "#FFB5A0",
            "onPrimaryFixedVariant": "#691800",
            "secondaryFixed": "#FFDBCF",
            "onSecondaryFixed": "#210B03",
            "secondaryFixedDim": "#EBBCAC",
            "onSecondaryFixedVariant": "#4D2F23",
            "tertiaryFixed": "#FFDCBE",
            "onTertiaryFixed": "#1E0D00",
            "tertiaryFixedDim": "#FFB870",
            "onTertiaryFixedVariant": "#522D00",
            "surfaceDim": "#141312",
            "surfaceBright": "#464442",
            "surfaceContainerLowest": "#080706",
            "surfaceContainerLow": "#1F1D1C",
            "surfaceContainer": "#292826",
            "surfaceContainerHigh": "#343231",
            "surfaceContainerHighest": "#3F3D3C"
        },
        "dark-high-contrast": {
            "primary": "#FFECE7",
            "surfaceTint": "#FFB5A0",
            "onPrimary": "#000000",
            "primaryContainer": "#FFAF98",
            "onPrimaryContainer": "#1E0300",
            "secondary": "#FFECE6",
            "onSecondary": "#000000",
            "secondaryContainer": "#E7B8A8",
            "onSecondaryContainer": "#1A0501",
            "tertiary": "#FFEDDF",
            "onTertiary": "#000000",
            "tertiaryContainer": "#FFB363",
            "onTertiaryContainer": "#150800",
            "error": "#FFECE9",
            "onError": "#000000",
            "errorContainer": "#FFAEA6",
            "onErrorContainer": "#220001",
            "background": "#1E100C",
            "onBackground": "#FADCD4",
            "surface": "#141312",
            "onSurface": "#FFFFFF",
            "surfaceVariant": "#444748",
            "onSurfaceVariant": "#FFFFFF",
            "outline": "#EEF0F1",
            "outlineVariant": "#C0C3C4",
            "shadow": "#000000",
            "scrim": "#000000",
            "inverseSurface": "#E6E2DF",
            "inverseOnSurface": "#000000",
            "inversePrimary": "#892200",
            "primaryFixed": "#FFDBD1",
            "onPrimaryFixed": "#000000",
            "primaryFixedDim": "#FFB5A0",
            "onPrimaryFixedVariant": "#280500",
            "secondaryFixed": "#FFDBCF",
            "onSecondaryFixed": "#000000",
            "secondaryFixedDim": "#EBBCAC",
            "onSecondaryFixedVariant": "#210B03",
            "tertiaryFixed": "#FFDCBE",
            "onTertiaryFixed": "#000000",
            "tertiaryFixedDim": "#FFB870",
            "onTertiaryFixedVariant": "#1E0D00",
            "surfaceDim": "#141312",
            "surfaceBright": "#52504E",
            "surfaceContainerLowest": "#000000",
            "surfaceContainerLow": "#211F1E",
            "surfaceContainer": "#32302F",
            "surfaceContainerHigh": "#3D3B39",
            "surfaceContainerHighest": "#484645"
        }
    },
    "palettes": {
        "primary": {
            "0": "#000000",
            "5": "#280500",
            "10": "#3B0900",
            "15": "#4D0F00",
            "20": "#5F1500",
            "25": "#731B00",
            "30": "#862200",
            "35": "#9B2800",
            "40": "#B02F00",
            "50": "#DB3E03",
            "60": "#FF5722",
            "70": "#FF8B69",
            "80": "#FFB5A0",
            "90": "#FFDBD1",
            "95": "#FFEDE8",
            "98": "#FFF8F6",
            "99": "#FFFBFF",
            "100": "#FFFFFF"
        },
        "secondary": {
            "0": "#000000",
            "5": "#210A03",
            "10": "#2E150B",
            "15": "#3A1F14",
            "20": "#46291E",
            "25": "#533428",
            "30": "#603F33",
            "35": "#6D4A3E",
            "40": "#7A5649",
            "50": "#956E60",
            "60": "#B18778",
            "70": "#CEA192",
            "80": "#EBBCAC",
            "90": "#FFDBCF",
            "95": "#FFEDE7",
            "98": "#FFF8F6",
            "99": "#FFFBFF",
            "100": "#FFFFFF"
        },
        "tertiary": {
            "0": "#000000",
            "5": "#1D0D00",
            "10": "#2C1600",
            "15": "#3B1F00",
            "20": "#4A2800",
            "25": "#593200",
            "30": "#693C00",
            "35": "#7A4600",
            "40": "#8B5000",
            "50": "#AE6600",
            "60": "#D27C00",
            "70": "#F79300",
            "80": "#FFB870",
            "90": "#FFDCBE",
            "95": "#FFEEE1",
            "98": "#FFF8F5",
            "99": "#FFFBFF",
            "100": "#FFFFFF"
        },
        "neutral": {
            "0": "#000000",
            "5": "#121110",
            "10": "#1C1B1A",
            "15": "#272525",
            "20": "#31302F",
            "25": "#3D3B3A",
            "30": "#484645",
            "35": "#545251",
            "40": "#605E5D",
            "50": "#797675",
            "60": "#93908F",
            "70": "#AEAAA9",
            "80": "#CAC6C4",
            "90": "#E6E2E0",
            "95": "#F4F0EE",
            "98": "#FDF8F6",
            "99": "#FFFBFF",
            "100": "#FFFFFF"
        },
        "neutral-variant": {
            "0": "#000000",
            "5": "#111111",
            "10": "#1C1B1B",
            "15": "#262625",
            "20": "#313030",
            "25": "#3C3B3B",
            "30": "#474646",
            "35": "#535252",
            "40": "#5F5E5E",
            "50": "#787776",
            "60": "#929090",
            "70": "#ADABAA",
            "80": "#C9C6C5",
            "90": "#E5E2E1",
            "95": "#F4F0EF",
            "98": "#FCF8F8",
            "99": "#F6FEFF",
            "100": "#FFFFFF"
        }
    }
}